caf/ntem/__init__.py
caf/ntem/__main__.py
caf/ntem/_version.py
caf/ntem/build.py
caf/ntem/inputs.py
caf/ntem/ntem_constants.py
caf/ntem/py.typed
caf/ntem/queries.py
caf/ntem/structure.py
caf_ntem-0.3.0.dist-info/licenses/LICENSE
caf_ntem-0.3.0.dist-info/METADATA
caf_ntem-0.3.0.dist-info/WHEEL
caf_ntem-0.3.0.dist-info/entry_points.txt
caf_ntem-0.3.0.dist-info/top_level.txt
caf_ntem-0.3.0.dist-info/RECORD
