Metadata-Version: 2.4
Name: caf.ntem
Version: 0.3.0
Summary: CAF package for extracting and analysing NTEM data.
Author: Transport for the North
License: Copyright © Transport for the North (“TfN”) (2025).
Project-URL: Bug Tracker, https://github.com/transport-for-the-north/caf.ntem/issues
Project-URL: Homepage, https://github.com/transport-for-the-north/caf.ntem
Project-URL: Source, https://github.com/transport-for-the-north/caf.ntem
Project-URL: Documentation, http://cafntem.rtfd.io/
Classifier: Programming Language :: Python :: 3 :: Only
Classifier: Programming Language :: Python :: 3.11
Classifier: Programming Language :: Python :: 3.12
Classifier: Programming Language :: Python :: 3.13
Requires-Python: >=3.10
License-File: LICENSE
Requires-Dist: pandas>=2.2.3
Requires-Dist: tqdm>=4.67.1
Requires-Dist: caf.toolkit>=0.9.0
Requires-Dist: sqlalchemy>=2.0.37
Requires-Dist: caf.base>=0.2.0
Requires-Dist: pydantic>=2
Provides-Extra: dev
Requires-Dist: black>=24; extra == "dev"
Requires-Dist: mypy>=1.10; extra == "dev"
Requires-Dist: mypy_extensions>=1.0.0; extra == "dev"
Requires-Dist: pydocstyle[toml]>=6.3; extra == "dev"
Requires-Dist: pylint>=3.2; extra == "dev"
Requires-Dist: isort>=5.13; extra == "dev"
Requires-Dist: pytest>=8.3; extra == "dev"
Requires-Dist: pytest-cov>=5.0; extra == "dev"
Requires-Dist: pytest-xdist>=3.6; extra == "dev"
Requires-Dist: versioningit>=3.1; extra == "dev"
Provides-Extra: docs
Requires-Dist: sphinx>=7.1.2; extra == "docs"
Requires-Dist: pydata-sphinx-theme>=0.14.1; extra == "docs"
Requires-Dist: graphviz>=0.20.1; extra == "docs"
Requires-Dist: sphinx-gallery>=0.17.1; extra == "docs"
Requires-Dist: matplotlib; extra == "docs"
Requires-Dist: sphinx-argparse>=0.5.2; extra == "docs"
Provides-Extra: build-db
Requires-Dist: sqlalchemy-access>=2.0.3; extra == "build-db"
Dynamic: license-file
